{
  "timestamp": "2026-01-19T18:00:04.825181",
  "games": [
    {
      "away_team": "Atlanta Hawks",
      "home_team": "Milwaukee Bucks",
      "spread": {
        "home": {
          "line": -1.5,
          "odds": -110,
          "tickets_pct": 38,
          "money_pct": 37
        },
        "away": {
          "line": 1.5,
          "odds": -110,
          "tickets_pct": 62,
          "money_pct": 63
        }
      },
      "moneyline": {
        "home": {
          "odds": -119,
          "tickets_pct": 75,
          "money_pct": 55
        },
        "away": {
          "odds": -100,
          "tickets_pct": 25,
          "money_pct": 45
        }
      },
      "total": {
        "under": {
          "line": 232.5,
          "odds": -110,
          "tickets_pct": 26,
          "money_pct": 24
        },
        "over": {
          "line": 232.5,
          "odds": -110,
          "tickets_pct": 74,
          "money_pct": 76
        }
      },
      "sharp_signals": [
        {
          "type": "MONEY_SPLIT",
          "market": "moneyline",
          "side": "Atlanta Hawks",
          "tickets_pct": 25,
          "money_pct": 45,
          "diff": 20
        }
      ],
      "sport": "NBA"
    },
    {
      "away_team": "Cleveland Cavaliers",
      "home_team": "Oklahoma City Thunder",
      "spread": {
        "away": {
          "line": -6.5,
          "odds": -102,
          "tickets_pct": 60,
          "money_pct": 61
        },
        "home": {
          "line": 6.5,
          "odds": -118,
          "tickets_pct": 40,
          "money_pct": 39
        }
      },
      "moneyline": {
        "away": {
          "odds": -222,
          "tickets_pct": 75,
          "money_pct": 76
        },
        "home": {
          "odds": 184,
          "tickets_pct": 25,
          "money_pct": 24
        }
      },
      "total": {
        "under": {
          "line": 229.5,
          "odds": -108,
          "tickets_pct": 16,
          "money_pct": 10
        },
        "over": {
          "line": 229.5,
          "odds": -115,
          "tickets_pct": 84,
          "money_pct": 90
        }
      },
      "sharp_signals": [],
      "sport": "NBA"
    },
    {
      "away_team": "Washington Wizards",
      "home_team": "Los Angeles Clippers",
      "spread": {
        "home": {
          "line": 6.5,
          "odds": -110,
          "tickets_pct": 19,
          "money_pct": 23
        },
        "away": {
          "line": -6.5,
          "odds": -110,
          "tickets_pct": 81,
          "money_pct": 77
        }
      },
      "moneyline": {
        "away": {
          "odds": -265,
          "tickets_pct": 90,
          "money_pct": 87
        },
        "home": {
          "odds": 210,
          "tickets_pct": 10,
          "money_pct": 13
        }
      },
      "total": {
        "under": {
          "line": 227,
          "odds": -110,
          "tickets_pct": 24,
          "money_pct": 23
        },
        "over": {
          "line": 227,
          "odds": -110,
          "tickets_pct": 76,
          "money_pct": 77
        }
      },
      "sharp_signals": [],
      "sport": "NBA"
    },
    {
      "away_team": "New York Knicks",
      "home_team": "Dallas Mavericks",
      "spread": {
        "home": {
          "line": -12.5,
          "odds": -115,
          "tickets_pct": 31,
          "money_pct": 40
        },
        "away": {
          "line": 12.5,
          "odds": -105,
          "tickets_pct": 69,
          "money_pct": 60
        }
      },
      "moneyline": {
        "home": {
          "odds": -550,
          "tickets_pct": 90,
          "money_pct": 87
        },
        "away": {
          "odds": 410,
          "tickets_pct": 10,
          "money_pct": 13
        }
      },
      "total": {
        "under": {
          "line": 231.5,
          "odds": -105,
          "tickets_pct": 22,
          "money_pct": 17
        },
        "over": {
          "line": 231.5,
          "odds": -115,
          "tickets_pct": 78,
          "money_pct": 83
        }
      },
      "sharp_signals": [],
      "sport": "NBA"
    },
    {
      "away_team": "Utah Jazz",
      "home_team": "San Antonio Spurs",
      "spread": {
        "away": {
          "line": 16.5,
          "odds": -110,
          "tickets_pct": 68,
          "money_pct": 72
        },
        "home": {
          "line": -16.5,
          "odds": -110,
          "tickets_pct": 32,
          "money_pct": 28
        }
      },
      "moneyline": {
        "home": {
          "odds": -1000,
          "tickets_pct": 89,
          "money_pct": 61
        },
        "away": {
          "odds": 650,
          "tickets_pct": 11,
          "money_pct": 39
        }
      },
      "total": {
        "under": {
          "line": 237.5,
          "odds": -110,
          "tickets_pct": 22,
          "money_pct": 20
        },
        "over": {
          "line": 237.5,
          "odds": -108,
          "tickets_pct": 78,
          "money_pct": 80
        }
      },
      "sharp_signals": [
        {
          "type": "MONEY_SPLIT",
          "market": "moneyline",
          "side": "Utah Jazz",
          "tickets_pct": 11,
          "money_pct": 39,
          "diff": 28
        }
      ],
      "sport": "NBA"
    },
    {
      "away_team": "Philadelphia 76ers",
      "home_team": "Indiana Pacers",
      "spread": {
        "away": {
          "line": 6.5,
          "odds": -125,
          "tickets_pct": 40,
          "money_pct": 39
        },
        "home": {
          "line": -6.5,
          "odds": -105,
          "tickets_pct": 60,
          "money_pct": 61
        }
      },
      "moneyline": {
        "home": {
          "odds": -259,
          "tickets_pct": 89,
          "money_pct": 91
        },
        "away": {
          "odds": 210,
          "tickets_pct": 11,
          "money_pct": 9
        }
      },
      "total": {
        "over": {
          "line": 220.5,
          "odds": -115,
          "tickets_pct": 0,
          "money_pct": 0
        },
        "under": {
          "line": 220.5,
          "odds": -148,
          "tickets_pct": 0,
          "money_pct": 0
        }
      },
      "sharp_signals": [],
      "sport": "NBA"
    },
    {
      "away_team": "Brooklyn Nets",
      "home_team": "Phoenix Suns",
      "spread": {
        "away": {
          "line": -8.5,
          "odds": -120,
          "tickets_pct": 0,
          "money_pct": 0
        },
        "home": {
          "line": 9.5,
          "odds": -115,
          "tickets_pct": 31,
          "money_pct": 30
        }
      },
      "moneyline": {
        "away": {
          "odds": -395,
          "tickets_pct": 89,
          "money_pct": 90
        },
        "home": {
          "odds": 310,
          "tickets_pct": 11,
          "money_pct": 10
        }
      },
      "total": {
        "under": {
          "line": 214.5,
          "odds": -110,
          "tickets_pct": 16,
          "money_pct": 16
        },
        "over": {
          "line": 214.5,
          "odds": -110,
          "tickets_pct": 84,
          "money_pct": 84
        }
      },
      "sharp_signals": [],
      "sport": "NBA"
    },
    {
      "away_team": "Boston Celtics",
      "home_team": "Detroit Pistons",
      "spread": {
        "home": {
          "line": -2.5,
          "odds": -110,
          "tickets_pct": 37,
          "money_pct": 36
        },
        "away": {
          "line": 1.5,
          "odds": -120,
          "tickets_pct": 0,
          "money_pct": 0
        }
      },
      "moneyline": {
        "home": {
          "odds": -125,
          "tickets_pct": 0,
          "money_pct": 0
        },
        "away": {
          "odds": 115,
          "tickets_pct": 29,
          "money_pct": 34
        }
      },
      "total": {
        "over": {
          "line": 223.5,
          "odds": -115,
          "tickets_pct": 0,
          "money_pct": 0
        },
        "under": {
          "line": 223.5,
          "odds": -112,
          "tickets_pct": 18,
          "money_pct": 24
        }
      },
      "sharp_signals": [],
      "sport": "NBA"
    },
    {
      "away_team": "Miami Heat",
      "home_team": "Golden State Warriors",
      "spread": {
        "home": {
          "line": -4.5,
          "odds": -115,
          "tickets_pct": 52,
          "money_pct": 46
        },
        "away": {
          "line": 4.5,
          "odds": -105,
          "tickets_pct": 48,
          "money_pct": 54
        }
      },
      "moneyline": {
        "away": {
          "odds": 162,
          "tickets_pct": 22,
          "money_pct": 33
        },
        "home": {
          "odds": -194,
          "tickets_pct": 78,
          "money_pct": 67
        }
      },
      "total": {
        "under": {
          "line": 239.5,
          "odds": -110,
          "tickets_pct": 32,
          "money_pct": 39
        },
        "over": {
          "line": 239.5,
          "odds": -110,
          "tickets_pct": 68,
          "money_pct": 61
        }
      },
      "sharp_signals": [
        {
          "type": "MONEY_SPLIT",
          "market": "moneyline",
          "side": "Miami Heat",
          "tickets_pct": 22,
          "money_pct": 33,
          "diff": 11
        }
      ],
      "sport": "NBA"
    },
    {
      "away_team": "New England Patriots",
      "home_team": "Denver Broncos",
      "spread": {
        "home": {
          "line": 5,
          "odds": -110,
          "tickets_pct": 27,
          "money_pct": 26
        },
        "away": {
          "line": -5,
          "odds": -120,
          "tickets_pct": 73,
          "money_pct": 74
        }
      },
      "moneyline": {
        "home": {
          "odds": 205,
          "tickets_pct": 18,
          "money_pct": 12
        },
        "away": {
          "odds": -250,
          "tickets_pct": 82,
          "money_pct": 88
        }
      },
      "total": {
        "under": {
          "line": 41.5,
          "odds": -110,
          "tickets_pct": 32,
          "money_pct": 32
        },
        "over": {
          "line": 41.5,
          "odds": -110,
          "tickets_pct": 68,
          "money_pct": 68
        }
      },
      "sharp_signals": [],
      "sport": "NFL"
    },
    {
      "away_team": "Seattle Seahawks",
      "home_team": "Los Angeles Rams",
      "spread": {
        "away": {
          "line": 2.5,
          "odds": -102,
          "tickets_pct": 52,
          "money_pct": 59
        },
        "home": {
          "line": -2.5,
          "odds": -118,
          "tickets_pct": 48,
          "money_pct": 41
        }
      },
      "moneyline": {
        "away": {
          "odds": 130,
          "tickets_pct": 25,
          "money_pct": 41
        },
        "home": {
          "odds": -155,
          "tickets_pct": 75,
          "money_pct": 59
        }
      },
      "total": {
        "under": {
          "line": 47.5,
          "odds": -110,
          "tickets_pct": 29,
          "money_pct": 26
        },
        "over": {
          "line": 47.5,
          "odds": -110,
          "tickets_pct": 71,
          "money_pct": 74
        }
      },
      "sharp_signals": [
        {
          "type": "MONEY_SPLIT",
          "market": "moneyline",
          "side": "Seattle Seahawks",
          "tickets_pct": 25,
          "money_pct": 41,
          "diff": 16
        }
      ],
      "sport": "NFL"
    },
    {
      "away_team": "Buffalo Sabres",
      "home_team": "Carolina Hurricanes",
      "spread": {
        "home": {
          "line": -1.5,
          "odds": 130,
          "tickets_pct": 60,
          "money_pct": 60
        },
        "away": {
          "line": 1.5,
          "odds": -155,
          "tickets_pct": 40,
          "money_pct": 40
        }
      },
      "moneyline": {
        "away": {
          "odds": 155,
          "tickets_pct": 13,
          "money_pct": 46
        },
        "home": {
          "odds": -185,
          "tickets_pct": 87,
          "money_pct": 54
        }
      },
      "total": {
        "under": {
          "line": 6.5,
          "odds": -108,
          "tickets_pct": 5,
          "money_pct": 3
        },
        "over": {
          "line": 6.5,
          "odds": -110,
          "tickets_pct": 95,
          "money_pct": 97
        }
      },
      "sharp_signals": [
        {
          "type": "MONEY_SPLIT",
          "market": "moneyline",
          "side": "Buffalo Sabres",
          "tickets_pct": 13,
          "money_pct": 46,
          "diff": 33
        }
      ],
      "sport": "NHL"
    },
    {
      "away_team": "Colorado Avalanche",
      "home_team": "Washington Capitals",
      "spread": {
        "away": {
          "line": 1.5,
          "odds": -130,
          "tickets_pct": 20,
          "money_pct": 17
        },
        "home": {
          "line": -1.5,
          "odds": 110,
          "tickets_pct": 80,
          "money_pct": 83
        }
      },
      "moneyline": {
        "away": {
          "odds": 180,
          "tickets_pct": 9,
          "money_pct": 32
        },
        "home": {
          "odds": -218,
          "tickets_pct": 91,
          "money_pct": 68
        }
      },
      "total": {
        "under": {
          "line": 6.5,
          "odds": -105,
          "tickets_pct": 9,
          "money_pct": 4
        },
        "over": {
          "line": 6.5,
          "odds": -115,
          "tickets_pct": 91,
          "money_pct": 96
        }
      },
      "sharp_signals": [
        {
          "type": "MONEY_SPLIT",
          "market": "moneyline",
          "side": "Colorado Avalanche",
          "tickets_pct": 9,
          "money_pct": 32,
          "diff": 23
        }
      ],
      "sport": "NHL"
    },
    {
      "away_team": "Pittsburgh Penguins",
      "home_team": "Seattle Kraken",
      "spread": {
        "home": {
          "line": 1.5,
          "odds": -245,
          "tickets_pct": 74,
          "money_pct": 64
        },
        "away": {
          "line": -1.5,
          "odds": 200,
          "tickets_pct": 26,
          "money_pct": 36
        }
      },
      "moneyline": {
        "home": {
          "odds": 110,
          "tickets_pct": 35,
          "money_pct": 28
        },
        "away": {
          "odds": -130,
          "tickets_pct": 65,
          "money_pct": 72
        }
      },
      "total": {
        "under": {
          "line": 5.5,
          "odds": 110,
          "tickets_pct": 19,
          "money_pct": 10
        },
        "over": {
          "line": 5.5,
          "odds": -130,
          "tickets_pct": 81,
          "money_pct": 90
        }
      },
      "sharp_signals": [
        {
          "type": "MONEY_SPLIT",
          "market": "spread",
          "side": "Pittsburgh Penguins",
          "tickets_pct": 26,
          "money_pct": 36,
          "diff": 10
        }
      ],
      "sport": "NHL"
    },
    {
      "away_team": "San Jose Sharks",
      "home_team": "Florida Panthers",
      "spread": {
        "home": {
          "line": 1.5,
          "odds": 135,
          "tickets_pct": 0,
          "money_pct": 0
        },
        "away": {
          "line": -1.5,
          "odds": -175,
          "tickets_pct": 0,
          "money_pct": 0
        }
      },
      "moneyline": {
        "home": {
          "odds": -185,
          "tickets_pct": 88,
          "money_pct": 76
        },
        "away": {
          "odds": 150,
          "tickets_pct": 12,
          "money_pct": 24
        }
      },
      "total": {
        "over": {
          "line": 6.5,
          "odds": -110,
          "tickets_pct": 86,
          "money_pct": 91
        },
        "under": {
          "line": 6.5,
          "odds": -105,
          "tickets_pct": 14,
          "money_pct": 9
        }
      },
      "sharp_signals": [
        {
          "type": "MONEY_SPLIT",
          "market": "spread",
          "side": "Florida Panthers",
          "tickets_pct": 53,
          "money_pct": 66,
          "diff": 13
        },
        {
          "type": "MONEY_SPLIT",
          "market": "moneyline",
          "side": "Florida Panthers",
          "tickets_pct": 12,
          "money_pct": 24,
          "diff": 12
        },
        {
          "type": "MONEY_SPLIT",
          "market": "moneyline",
          "side": "San Jose Sharks",
          "tickets_pct": 12,
          "money_pct": 24,
          "diff": 12
        }
      ],
      "sport": "NHL"
    },
    {
      "away_team": "Minnesota Wild",
      "home_team": "Toronto Maple Leafs",
      "spread": {
        "home": {
          "line": 1.5,
          "odds": -170,
          "tickets_pct": 0,
          "money_pct": 0
        },
        "away": {
          "line": -1.5,
          "odds": 130,
          "tickets_pct": 0,
          "money_pct": 0
        }
      },
      "moneyline": {
        "home": {
          "odds": 147,
          "tickets_pct": 0,
          "money_pct": 0
        },
        "away": {
          "odds": -110,
          "tickets_pct": 33,
          "money_pct": 17
        }
      },
      "total": {
        "under": {
          "line": 6,
          "odds": -110,
          "tickets_pct": 14,
          "money_pct": 9
        },
        "over": {
          "line": 6,
          "odds": -110,
          "tickets_pct": 86,
          "money_pct": 91
        }
      },
      "sharp_signals": [
        {
          "type": "MONEY_SPLIT",
          "market": "moneyline",
          "side": "Toronto Maple Leafs",
          "tickets_pct": 67,
          "money_pct": 83,
          "diff": 16
        }
      ],
      "sport": "NHL"
    },
    {
      "away_team": "Philadelphia Flyers",
      "home_team": "Vegas Golden Knights",
      "spread": {
        "home": {
          "line": -1.5,
          "odds": 105,
          "tickets_pct": 72,
          "money_pct": 65
        },
        "away": {
          "line": 1.5,
          "odds": -130,
          "tickets_pct": 28,
          "money_pct": 35
        }
      },
      "moneyline": {
        "away": {
          "odds": 188,
          "tickets_pct": 7,
          "money_pct": 2
        },
        "home": {
          "odds": -230,
          "tickets_pct": 93,
          "money_pct": 98
        }
      },
      "total": {
        "under": {
          "line": 6.5,
          "odds": -120,
          "tickets_pct": 9,
          "money_pct": 5
        },
        "over": {
          "line": 6.5,
          "odds": -102,
          "tickets_pct": 91,
          "money_pct": 95
        }
      },
      "sharp_signals": [],
      "sport": "NHL"
    },
    {
      "away_team": "Chicago Blackhawks",
      "home_team": "Winnipeg Jets",
      "spread": {
        "away": {
          "line": -1.5,
          "odds": 170,
          "tickets_pct": 48,
          "money_pct": 54
        },
        "home": {
          "line": 1.5,
          "odds": -205,
          "tickets_pct": 52,
          "money_pct": 46
        }
      },
      "moneyline": {
        "away": {
          "odds": -146,
          "tickets_pct": 78,
          "money_pct": 90
        },
        "home": {
          "odds": 122,
          "tickets_pct": 22,
          "money_pct": 10
        }
      },
      "total": {
        "under": {
          "line": 5.5,
          "odds": 105,
          "tickets_pct": 13,
          "money_pct": 8
        },
        "over": {
          "line": 5.5,
          "odds": -128,
          "tickets_pct": 87,
          "money_pct": 92
        }
      },
      "sharp_signals": [
        {
          "type": "MONEY_SPLIT",
          "market": "moneyline",
          "side": "Chicago Blackhawks",
          "tickets_pct": 78,
          "money_pct": 90,
          "diff": 12
        }
      ],
      "sport": "NHL"
    },
    {
      "away_team": "Calgary Flames",
      "home_team": "New Jersey Devils",
      "spread": {
        "away": {
          "line": -1.5,
          "odds": 210,
          "tickets_pct": 24,
          "money_pct": 39
        },
        "home": {
          "line": 1.5,
          "odds": -258,
          "tickets_pct": 76,
          "money_pct": 61
        }
      },
      "moneyline": {
        "home": {
          "odds": -102,
          "tickets_pct": 41,
          "money_pct": 42
        },
        "away": {
          "odds": -118,
          "tickets_pct": 59,
          "money_pct": 58
        }
      },
      "total": {
        "over": {
          "line": 5.5,
          "odds": -132,
          "tickets_pct": 86,
          "money_pct": 85
        },
        "under": {
          "line": 5.5,
          "odds": 110,
          "tickets_pct": 14,
          "money_pct": 15
        }
      },
      "sharp_signals": [
        {
          "type": "MONEY_SPLIT",
          "market": "spread",
          "side": "Calgary Flames",
          "tickets_pct": 24,
          "money_pct": 39,
          "diff": 15
        }
      ],
      "sport": "NHL"
    },
    {
      "away_team": "Anaheim Ducks",
      "home_team": "New York Rangers",
      "spread": {
        "away": {
          "line": 1.5,
          "odds": -210,
          "tickets_pct": 64,
          "money_pct": 58
        },
        "home": {
          "line": -1.5,
          "odds": 170,
          "tickets_pct": 36,
          "money_pct": 42
        }
      },
      "moneyline": {
        "home": {
          "odds": -135,
          "tickets_pct": 77,
          "money_pct": 73
        },
        "away": {
          "odds": 114,
          "tickets_pct": 23,
          "money_pct": 27
        }
      },
      "total": {
        "under": {
          "line": 6.5,
          "odds": 110,
          "tickets_pct": 12,
          "money_pct": 11
        },
        "over": {
          "line": 6.5,
          "odds": -135,
          "tickets_pct": 88,
          "money_pct": 89
        }
      },
      "sharp_signals": [],
      "sport": "NHL"
    },
    {
      "away_team": "Vancouver Canucks",
      "home_team": "New York Islanders",
      "spread": {
        "home": {
          "line": 1.5,
          "odds": -210,
          "tickets_pct": 42,
          "money_pct": 16
        },
        "away": {
          "line": -1.5,
          "odds": 170,
          "tickets_pct": 58,
          "money_pct": 84
        }
      },
      "moneyline": {
        "home": {
          "odds": 120,
          "tickets_pct": 16,
          "money_pct": 11
        },
        "away": {
          "odds": -142,
          "tickets_pct": 84,
          "money_pct": 89
        }
      },
      "total": {
        "over": {
          "line": 5.5,
          "odds": -122,
          "tickets_pct": 89,
          "money_pct": 91
        },
        "under": {
          "line": 5.5,
          "odds": 102,
          "tickets_pct": 11,
          "money_pct": 9
        }
      },
      "sharp_signals": [
        {
          "type": "MONEY_SPLIT",
          "market": "spread",
          "side": "Vancouver Canucks",
          "tickets_pct": 58,
          "money_pct": 84,
          "diff": 26
        }
      ],
      "sport": "NHL"
    }
  ]
}