[
  {
    "Sport": "Soccer",
    "League": "",
    "Date": "11/12/2025",
    "Picks": "2 Team Parlay: Portugal ML, Germany ML",
    "Odds": "",
    "Units": "",
    "Result": "L",
    "ProfitLoss": "-6.48",
    "GradedAt": ""
  },
  {
    "Sport": "Soccer",
    "League": "",
    "Date": "11/4/2025",
    "Picks": "Olympiakos/PSV over 2.5",
    "Odds": "",
    "Units": "",
    "Result": "L",
    "ProfitLoss": "-2.77",
    "GradedAt": ""
  },
  {
    "Sport": "Soccer",
    "League": "",
    "Date": "11/3/2025",
    "Picks": "Cagliari/Lazio  Under 2.5 Goals",
    "Odds": "",
    "Units": "",
    "Result": "W",
    "ProfitLoss": "0.5",
    "GradedAt": ""
  },
  {
    "Sport": "Soccer",
    "League": "",
    "Date": "10/29/2025",
    "Picks": "Chelsea ML",
    "Odds": "",
    "Units": "",
    "Result": "W",
    "ProfitLoss": "1",
    "GradedAt": ""
  },
  {
    "Sport": "Soccer",
    "League": "",
    "Date": "10/25/2025",
    "Picks": "Real Oviedo/ Girona Under 2.5 Goals",
    "Odds": "",
    "Units": "",
    "Result": "L",
    "ProfitLoss": "-1.23",
    "GradedAt": ""
  },
  {
    "Sport": "Soccer",
    "League": "",
    "Date": "10/14/2025",
    "Picks": "Armenia Ireland Total Corners under 8.5",
    "Odds": "",
    "Units": "",
    "Result": "W",
    "ProfitLoss": "1",
    "GradedAt": ""
  }
]