[
 {
  "file": "spurs-at-knicks-nba-analysis-stats-preview.html",
  "sport": "nba",
  "family": "featured",
  "h1": "Spurs at Knicks Analysis Stats Preview March 1 2026",
  "issues": [
   "og_image_logo_or_missing",
   "no_faqpage_schema"
  ]
 },
 {
  "file": "spurs-relegation-crisis-crystal-palace-coupe-de-france-lens-soccer.html",
  "sport": "soccer",
  "family": "board",
  "h1": "Soccer March 5, 2026",
  "issues": [
   "og_image_logo_or_missing"
  ]
 },
 {
  "file": "spurs-vs-thunder-western-conference-final-game-5-analysis-stats-preview.html",
  "sport": "unknown",
  "family": "featured",
  "h1": "Spurs at Thunder - Western Conference Finals Game 5",
  "issues": [
   "og_image_logo_or_missing",
   "no_faqpage_schema",
   "no_sportsevent_schema"
  ]
 },
 {
  "file": "spurs-vs-thunder-western-conference-final-game-7-nba-analysis-stats-preview.html",
  "sport": "nba",
  "family": "featured",
  "h1": "Spurs at Thunder - Western Conference Final Game 7",
  "issues": [
   "og_image_logo_or_missing",
   "no_faqpage_schema",
   "no_sportsevent_schema"
  ]
 },
 {
  "file": "spurs-vs-warriors-nba-analysis-stats-preview.html",
  "sport": "nba",
  "family": "featured",
  "h1": "Spurs vs Warriors Analysis Stats Preview April 1 2026",
  "issues": [
   "og_image_hotlink_risky"
  ]
 },
 {
  "file": "st-pauli-koln-relegation-battle-bundesliga-soccer.html",
  "sport": "soccer",
  "family": "board",
  "h1": "St. Pauli vs K\u00f6ln: Relegation Six-Pointer at Millerntor",
  "issues": [
   "og_image_logo_or_missing"
  ]
 },
 {
  "file": "strider-alcantara-mize-thursday-seven-game-mlb.html",
  "sport": "mlb",
  "family": "board",
  "h1": "Strider-Alcantara Headlines A Seven-Game Thursday",
  "issues": [
   "og_image_logo_or_missing"
  ]
 },
 {
  "file": "stuttgart-freiburg-dfb-pokal-semifinal-la-liga-soccer.html",
  "sport": "soccer",
  "family": "board",
  "h1": "DFB-Pokal Semifinal Stuttgart-Freiburg Anchors A Full Thursday European Slate",
  "issues": [
   "og_image_logo_or_missing"
  ]
 },
 {
  "file": "suns-vs-lakers-analysis-stats-preview.html",
  "sport": "unknown",
  "family": "featured",
  "h1": "Suns vs Lakers NBA Preview April 10 2026",
  "issues": [
   "og_image_logo_or_missing"
  ]
 },
 {
  "file": "sweden-vs-norway-scandinavian-derby-world-cup-tuneup-soccer-analysis-stats-preview.html",
  "sport": "soccer",
  "family": "featured",
  "h1": "Sweden at Norway - The Scandinavian Derby",
  "issues": [
   "og_image_logo_or_missing",
   "no_faqpage_schema",
   "no_sportsevent_schema"
  ]
 },
 {
  "file": "thunder-at-knicks-nba-analysis-stats-preview.html",
  "sport": "nba",
  "family": "featured",
  "h1": "Thunder at Knicks NBA Analysis Stats Preview March 4 2026",
  "issues": [
   "og_image_logo_or_missing",
   "no_faqpage_schema"
  ]
 },
 {
  "file": "thunder-vs-spurs-analysis-stats-preview.html",
  "sport": "unknown",
  "family": "featured",
  "h1": "Thunder at Spurs - Western Conference Finals Game 3",
  "issues": [
   "og_image_logo_or_missing",
   "no_faqpage_schema",
   "no_sportsevent_schema"
  ]
 },
 {
  "file": "thunder-vs-spurs-western-conference-final-game-6-nba-analysis-stats-preview.html",
  "sport": "nba",
  "family": "featured",
  "h1": "Thunder at Spurs - Western Conference Final Game 6",
  "issues": [
   "og_image_logo_or_missing",
   "no_faqpage_schema",
   "no_sportsevent_schema"
  ]
 },
 {
  "file": "thunder-vs-spurs-western-conference-finals-game-4-analysis-stats-preview.html",
  "sport": "unknown",
  "family": "featured",
  "h1": "Thunder at Spurs - Western Conference Finals Game 4",
  "issues": [
   "og_image_logo_or_missing",
   "no_faqpage_schema",
   "no_sportsevent_schema"
  ]
 },
 {
  "file": "timberwolves-vs-nuggets-nba-analysis-stats-preview.html",
  "sport": "nba",
  "family": "featured",
  "h1": "Timberwolves vs Nuggets Game 2 Analysis April 20 2026",
  "issues": [
   "og_image_logo_or_missing"
  ]
 }
]