[
 {
  "file": "cavs-lakers-luka-mitchell-showdown-raptors-visit-pistons-nba.html",
  "sport": "nba",
  "family": "board",
  "h1": "NBA March 31, 2026",
  "issues": [
   "og_image_logo_or_missing"
  ]
 },
 {
  "file": "celtics-76ers-game-7-winner-take-all-east-saturday-nba.html",
  "sport": "nba",
  "family": "board",
  "h1": "The East Bracket Comes Down To One Night - 76ers At Celtics In A Winner-Take-All Game 7 At TD Garden",
  "issues": [
   "og_image_logo_or_missing"
  ]
 },
 {
  "file": "celtics-at-mavericks-prediction-picks.html",
  "sport": "unknown",
  "family": "prediction-picks",
  "h1": "NBA: Boston Celtics @ Dallas Mavericks - February 3, 2026",
  "issues": [
   "og_image_logo_or_missing"
  ]
 },
 {
  "file": "celtics-bucks-playoff-positioning-nba.html",
  "sport": "nba",
  "family": "board",
  "h1": "NBA March 2, 2026",
  "issues": [
   "og_image_logo_or_missing"
  ]
 },
 {
  "file": "celtics-depleted-cavs-knicks-lakers-abc-doubleheader-nba.html",
  "sport": "nba",
  "family": "board",
  "h1": "NBA March 8, 2026",
  "issues": [
   "og_image_logo_or_missing"
  ]
 },
 {
  "file": "celtics-knicks-east-heavyweight-lakers-warriors-rivalry-nba.html",
  "sport": "nba",
  "family": "board",
  "h1": "NBA Previews Today",
  "issues": [
   "og_image_logo_or_missing"
  ]
 },
 {
  "file": "celtics-thunder-contender-clash-pistons-surge-nba.html",
  "sport": "nba",
  "family": "board",
  "h1": "NBA March 12, 2026",
  "issues": [
   "og_image_logo_or_missing"
  ]
 },
 {
  "file": "clippers-vs-lakers-prediction-picks.html",
  "sport": "unknown",
  "family": "prediction-picks",
  "h1": "Clippers vs Lakers Game Picks & Prediction - November 25, 2025",
  "issues": [
   "og_image_logo_or_missing"
  ]
 },
 {
  "file": "conference-tournament-chaos-big-ten-big-12-acc-tip-off-college-basketball.html",
  "sport": "ncaab",
  "family": "board",
  "h1": "College Basketball March 10, 2026",
  "issues": [
   "og_image_logo_or_missing"
  ]
 },
 {
  "file": "conference-tournament-madness-dybantsa-sec-big-12-college-basketball.html",
  "sport": "ncaab",
  "family": "board",
  "h1": "College Basketball March 11, 2026",
  "issues": [
   "og_image_logo_or_missing"
  ]
 },
 {
  "file": "curry-booker-play-in-finale-hornets-magic-east-seed-nba.html",
  "sport": "nba",
  "family": "board",
  "h1": "Curry, Booker, and the Last Two Playoff Spots",
  "issues": [
   "og_image_logo_or_missing"
  ]
 },
 {
  "file": "curry-returns-lakers-visit-flagg-mavs-11-game-sunday-nba.html",
  "sport": "nba",
  "family": "board",
  "h1": "NBA Previews Today",
  "issues": [
   "og_image_logo_or_missing"
  ]
 },
 {
  "file": "dallas-stars-vs-san-jose-sharks-prediction-picks.html",
  "sport": "unknown",
  "family": "prediction-picks",
  "h1": "Dallas Stars vs San Jose Sharks Picks & Prediction - December 18, 2025",
  "issues": [
   "og_image_logo_or_missing"
  ]
 },
 {
  "file": "devils-moneyline-plus-110-at-capitals-nhl.html",
  "sport": "nhl",
  "family": "board",
  "h1": "Play of the Day",
  "issues": [
   "og_image_hotlink_risky",
   "needs_manual_structure"
  ]
 },
 {
  "file": "devils-rangers-hudson-river-rivalry-stars-bruins-clash-nhl.html",
  "sport": "nhl",
  "family": "board",
  "h1": "NHL March 31, 2026",
  "issues": [
   "og_image_logo_or_missing"
  ]
 }
]