{
  "timestamp": "2025-12-04T10:37:22.081031",
  "key": "ncaab_stats_2520",
  "data": {
    "avgRebounds": "39.5",
    "assistTurnoverRatio": "0.5",
    "avgFouls": "20.0",
    "gamesPlayed": "6",
    "gamesStarted": "0",
    "minutes": "1200",
    "avgMinutes": "200.0",
    "totalRebounds": "237",
    "rebounds": "237",
    "freeThrowPct": "73.5",
    "avgFieldGoalsMade": "20.2",
    "avgFieldGoalsAttempted": "57.7",
    "avgThreePointFieldGoalsMade": "4.2",
    "avgThreePointFieldGoalsAttempted": "17.3",
    "avgFreeThrowsMade": "16.7",
    "avgFreeThrowsAttempted": "22.7",
    "avgPoints": "61.2",
    "avgOffensiveRebounds": "14.5",
    "avgAssists": "8.3",
    "avgTurnovers": "15.3",
    "twoPointFieldGoalPct": "39.7",
    "scoringEfficiency": "1.061",
    "shootingEfficiency": "0.39",
    "fieldGoalPct": "35.0",
    "twoPointFieldGoalsMade": "96.0",
    "twoPointFieldGoalsAttempted": "242.0",
    "points": "367",
    "offensiveRebounds": "87",
    "assists": "50",
    "turnovers": "92",
    "fieldGoalsMade": "121",
    "fieldGoalsAttempted": "346",
    "freeThrowsMade": "100",
    "freeThrowsAttempted": "136",
    "threePointFieldGoalsMade": "25",
    "threePointFieldGoalsAttempted": "104",
    "threePointFieldGoalPct": "24.0",
    "avgTwoPointFieldGoalsMade": "16.0",
    "avgTwoPointFieldGoalsAttempted": "40.3",
    "avgDefensiveRebounds": "25.0",
    "avgBlocks": "3.7",
    "avgSteals": "5.7",
    "defensiveRebounds": "150",
    "steals": "34",
    "blocks": "22",
    "avgPointsFor": 0.0,
    "avgPointsAgainst": 0.0,
    "pointDifferential": 0.0,
    "wins": 0.0,
    "losses": 0.0,
    "point_diff": 0.0
  }
}