{
  "timestamp": "2025-12-04T10:30:59.262104",
  "key": "nba_advanced_3",
  "data": {
    "offensive_rating": 110.5,
    "defensive_rating": 120.7,
    "net_rating": -10.2,
    "pace": 100.6,
    "efg_pct": 51.7,
    "ts_pct": 55.6,
    "ast_ratio": 16.5,
    "ast_to_ratio": 1.6,
    "oreb_pct": 31.6,
    "dreb_pct": 68.9,
    "reb_pct": 49.2,
    "tov_pct": 14.7,
    "pie": 0.4,
    "ast_pct": 57.4,
    "off_rating_rank": 26,
    "def_rating_rank": 29,
    "net_rating_rank": 28,
    "pace_rank": 19,
    "from_nba_stats": true
  }
}