{
  "timestamp": "2025-12-04T10:30:59.166766",
  "key": "nba_stats_3",
  "data": {
    "OTLosses": 0.0,
    "OTWins": 0.0,
    "avgPointsAgainst": 123.318184,
    "avgPointsFor": 112.59091,
    "differential": -10.700000000000003,
    "divisionWinPercent": 0.16666667,
    "gamesBehind": 18.0,
    "gamesPlayed": 22.0,
    "leagueWinPercent": 0.055555556,
    "losses": 19.0,
    "playoffSeed": 15.0,
    "pointDifferential": -236.0,
    "points": -8.0,
    "pointsAgainst": 2713.0,
    "pointsFor": 2477.0,
    "streak": -4.0,
    "ties": 0.0,
    "winPercent": 0.13636364,
    "wins": 3.0
  }
}