{
  "date": "2025-07-16",
  "games": [
    {
      "home_team": "National League",
      "away_team": "American League",
      "start_time": "00:00",
      "pitchers": {
        "home": "TBD",
        "away": "TBD"
      },
      "odds": {
        "moneyline": {},
        "total": {}
      }
    },
    {
      "home_team": "Diablos Rojos",
      "away_team": "Oaxaca",
      "start_time": "01:00",
      "pitchers": {
        "home": "TBD",
        "away": "TBD"
      },
      "odds": {
        "moneyline": {},
        "total": {}
      }
    },
    {
      "home_team": "Veracruz",
      "away_team": "Queretaro",
      "start_time": "01:00",
      "pitchers": {
        "home": "TBD",
        "away": "TBD"
      },
      "odds": {
        "moneyline": {},
        "total": {}
      }
    },
    {
      "home_team": "Puebla",
      "away_team": "Tabasco",
      "start_time": "01:00",
      "pitchers": {
        "home": "TBD",
        "away": "TBD"
      },
      "odds": {
        "moneyline": {},
        "total": {}
      }
    },
    {
      "home_team": "Chihuahua",
      "away_team": "Saltillo",
      "start_time": "01:00",
      "pitchers": {
        "home": "TBD",
        "away": "TBD"
      },
      "odds": {
        "moneyline": {},
        "total": {}
      }
    },
    {
      "home_team": "Dos Laredos",
      "away_team": "Toros de Tijuana",
      "start_time": "01:00",
      "pitchers": {
        "home": "TBD",
        "away": "TBD"
      },
      "odds": {
        "moneyline": {},
        "total": {}
      }
    },
    {
      "home_team": "Yucatan",
      "away_team": "Campeche",
      "start_time": "01:30",
      "pitchers": {
        "home": "TBD",
        "away": "TBD"
      },
      "odds": {
        "moneyline": {},
        "total": {}
      }
    },
    {
      "home_team": "Caliente de Durango",
      "away_team": "Laguna",
      "start_time": "01:35",
      "pitchers": {
        "home": "TBD",
        "away": "TBD"
      },
      "odds": {
        "moneyline": {},
        "total": {}
      }
    },
    {
      "home_team": "Monclova",
      "away_team": "Monterrey",
      "start_time": "01:45",
      "pitchers": {
        "home": "TBD",
        "away": "TBD"
      },
      "odds": {
        "moneyline": {},
        "total": {}
      }
    },
    {
      "home_team": "Fukuoka S. Hawks",
      "away_team": "Chiba Lotte Marines",
      "start_time": "09:00",
      "pitchers": {
        "home": "TBD",
        "away": "TBD"
      },
      "odds": {
        "moneyline": {},
        "total": {}
      }
    },
    {
      "home_team": "Hanshin Tigers",
      "away_team": "Chunichi Dragons",
      "start_time": "09:00",
      "pitchers": {
        "home": "TBD",
        "away": "TBD"
      },
      "odds": {
        "moneyline": {},
        "total": {}
      }
    },
    {
      "home_team": "Hiroshima Carp",
      "away_team": "Yokohama BayStars",
      "start_time": "09:00",
      "pitchers": {
        "home": "TBD",
        "away": "TBD"
      },
      "odds": {
        "moneyline": {},
        "total": {}
      }
    },
    {
      "home_team": "Orix Buffaloes",
      "away_team": "Rakuten Gold. Eagles",
      "start_time": "09:00",
      "pitchers": {
        "home": "TBD",
        "away": "TBD"
      },
      "odds": {
        "moneyline": {},
        "total": {}
      }
    },
    {
      "home_team": "Seibu Lions",
      "away_team": "Nippon Ham Fighters",
      "start_time": "09:00",
      "pitchers": {
        "home": "TBD",
        "away": "TBD"
      },
      "odds": {
        "moneyline": {},
        "total": {}
      }
    },
    {
      "home_team": "Wei Chuan Dragons",
      "away_team": "TSG Hawks",
      "start_time": "10:35",
      "pitchers": {
        "home": "TBD",
        "away": "TBD"
      },
      "odds": {
        "moneyline": {},
        "total": {}
      }
    },
    {
      "home_team": "Rakuten Monkeys",
      "away_team": "Chinatrust Brothers",
      "start_time": "10:35",
      "pitchers": {
        "home": "TBD",
        "away": "TBD"
      },
      "odds": {
        "moneyline": {},
        "total": {}
      }
    },
    {
      "home_team": "Uni Lions",
      "away_team": "Fubon Guardians",
      "start_time": "10:35",
      "pitchers": {
        "home": "TBD",
        "away": "TBD"
      },
      "odds": {
        "moneyline": {},
        "total": {}
      }
    },
    {
      "home_team": "Torre Pedrera",
      "away_team": "Modena",
      "start_time": "18:00",
      "pitchers": {
        "home": "TBD",
        "away": "TBD"
      },
      "odds": {
        "moneyline": {},
        "total": {}
      }
    },
    {
      "home_team": "Bravos de Leon",
      "away_team": "Quintana Roo",
      "start_time": "22:00",
      "pitchers": {
        "home": "TBD",
        "away": "TBD"
      },
      "odds": {
        "moneyline": {},
        "total": {}
      }
    },
    {
      "home_team": "Delfines de La Guaira",
      "away_team": "Samanes de Aragua",
      "start_time": "22:00",
      "pitchers": {
        "home": "TBD",
        "away": "TBD"
      },
      "odds": {
        "moneyline": {},
        "total": {}
      }
    },
    {
      "home_team": "Caciques de Distrito",
      "away_team": "Marineros de Carabobo",
      "start_time": "22:00",
      "pitchers": {
        "home": "TBD",
        "away": "TBD"
      },
      "odds": {
        "moneyline": {},
        "total": {}
      }
    },
    {
      "home_team": "Jalisco",
      "away_team": "Aguascalientes",
      "start_time": "23:00",
      "pitchers": {
        "home": "TBD",
        "away": "TBD"
      },
      "odds": {
        "moneyline": {},
        "total": {}
      }
    }
  ]
}